cronicle/__init__.py
cronicle/config.py
cronicle-0.4.0.dist-info/LICENSE
cronicle-0.4.0.dist-info/METADATA
cronicle-0.4.0.dist-info/WHEEL
cronicle-0.4.0.dist-info/entry_points.txt
cronicle-0.4.0.dist-info/top_level.txt
cronicle-0.4.0.dist-info/RECORD
