Metadata-Version: 2.1
Name: cronicle
Version: 0.4.0
Summary: Use cron to rotate backup files!
Home-page: https://github.com/KraYmer/cronicle
Author: Fabrice Laporte
Author-email: kraymer@gmail.com
License: MIT
Keywords: cron rotate backup
Platform: ALL
Classifier: License :: OSI Approved :: MIT License
Classifier: Programming Language :: Python
Classifier: Environment :: Console
Classifier: Topic :: System :: Filesystems
Requires-Dist: click
Requires-Dist: click-log
Requires-Dist: confuse
Requires-Dist: ordereddict
Requires-Dist: python-dateutil
Requires-Dist: pyyaml
Requires-Dist: six
Provides-Extra: test
Requires-Dist: coverage (<6,>=5) ; extra == 'test'
Requires-Dist: nose (>1.3) ; extra == 'test'
Requires-Dist: mock (==4.0.2) ; extra == 'test'
Requires-Dist: tox (>=3) ; extra == 'test'
